textstructify/__init__.py
textstructify/main.py
textstructify/prompts.py
textstructify-2025.12.21083245.dist-info/METADATA
textstructify-2025.12.21083245.dist-info/WHEEL
textstructify-2025.12.21083245.dist-info/top_level.txt
textstructify-2025.12.21083245.dist-info/RECORD
