Metadata-Version: 2.4
Name: textstructify
Version: 2025.12.21083245
Summary: A new package designed to transform raw text inputs into structured, meaningful outputs using advanced language models. This package leverages the capabilities of llmatch-messages to ensure that the r
Author-email: textstructify <hi@eugene.plus>
License: MIT
Project-URL: Homepage, https://github.com/chigwell/textstructify
Requires-Python: >=3.9
Requires-Dist: langchain-llm7>=0.0.0
Requires-Dist: llmatch-messages>=0.0.0
Requires-Dist: langchain-core>=0.3.0
